README.txt
setup.py
leveldb_cli.egg-info/PKG-INFO
leveldb_cli.egg-info/SOURCES.txt
leveldb_cli.egg-info/dependency_links.txt
leveldb_cli.egg-info/entry_points.txt
leveldb_cli.egg-info/requires.txt
leveldb_cli.egg-info/top_level.txt
leveldbcli/__init__.py
leveldbcli/app.py