Metadata-Version: 1.1
Name: leveldb-cli
Version: 0.1.0
Summary: A command-line interface for LevelDB databases.
Home-page: https://github.com/maurycyp/leveldb-cli
Author: Maurycy Pietrzak
Author-email: ['github.com@wayheavy.com']
License: Unlicense
Platform: UNKNOWN
Classifier: Development Status :: 3 - Alpha
Classifier: Intended Audience :: Developers
Classifier: License :: Public Domain
Classifier: Operating System :: OS Independent
Classifier: Programming Language :: Python
Classifier: Programming Language :: Python :: 2
Classifier: Topic :: Database
